evmosproto/__init__.py
evmosproto/cosmos/__init__.py
evmosproto/cosmos/auth/__init__.py
evmosproto/cosmos/auth/v1beta1/__init__.py
evmosproto/cosmos/auth/v1beta1/auth_pb2.py
evmosproto/cosmos/auth/v1beta1/auth_pb2_grpc.py
evmosproto/cosmos/auth/v1beta1/genesis_pb2.py
evmosproto/cosmos/auth/v1beta1/genesis_pb2_grpc.py
evmosproto/cosmos/auth/v1beta1/query_pb2.py
evmosproto/cosmos/auth/v1beta1/query_pb2_grpc.py
evmosproto/cosmos/authz/__init__.py
evmosproto/cosmos/authz/v1beta1/__init__.py
evmosproto/cosmos/authz/v1beta1/authz_pb2.py
evmosproto/cosmos/authz/v1beta1/authz_pb2_grpc.py
evmosproto/cosmos/authz/v1beta1/event_pb2.py
evmosproto/cosmos/authz/v1beta1/event_pb2_grpc.py
evmosproto/cosmos/authz/v1beta1/genesis_pb2.py
evmosproto/cosmos/authz/v1beta1/genesis_pb2_grpc.py
evmosproto/cosmos/authz/v1beta1/query_pb2.py
evmosproto/cosmos/authz/v1beta1/query_pb2_grpc.py
evmosproto/cosmos/authz/v1beta1/tx_pb2.py
evmosproto/cosmos/authz/v1beta1/tx_pb2_grpc.py
evmosproto/cosmos/bank/__init__.py
evmosproto/cosmos/bank/v1beta1/__init__.py
evmosproto/cosmos/bank/v1beta1/authz_pb2.py
evmosproto/cosmos/bank/v1beta1/authz_pb2_grpc.py
evmosproto/cosmos/bank/v1beta1/bank_pb2.py
evmosproto/cosmos/bank/v1beta1/bank_pb2_grpc.py
evmosproto/cosmos/bank/v1beta1/genesis_pb2.py
evmosproto/cosmos/bank/v1beta1/genesis_pb2_grpc.py
evmosproto/cosmos/bank/v1beta1/query_pb2.py
evmosproto/cosmos/bank/v1beta1/query_pb2_grpc.py
evmosproto/cosmos/bank/v1beta1/tx_pb2.py
evmosproto/cosmos/bank/v1beta1/tx_pb2_grpc.py
evmosproto/cosmos/base/__init__.py
evmosproto/cosmos/base/abci/__init__.py
evmosproto/cosmos/base/abci/v1beta1/__init__.py
evmosproto/cosmos/base/abci/v1beta1/abci_pb2.py
evmosproto/cosmos/base/abci/v1beta1/abci_pb2_grpc.py
evmosproto/cosmos/base/kv/__init__.py
evmosproto/cosmos/base/kv/v1beta1/__init__.py
evmosproto/cosmos/base/kv/v1beta1/kv_pb2.py
evmosproto/cosmos/base/kv/v1beta1/kv_pb2_grpc.py
evmosproto/cosmos/base/query/__init__.py
evmosproto/cosmos/base/query/v1beta1/__init__.py
evmosproto-1.0.4.dist-info/LICENSE
evmosproto-1.0.4.dist-info/METADATA
evmosproto-1.0.4.dist-info/WHEEL
evmosproto-1.0.4.dist-info/top_level.txt
evmosproto-1.0.4.dist-info/RECORD
